<?xml version="1.0" encoding="UTF-8"?>
<entity_profile>
<category_product><id_category><![CDATA[2]]></id_category>
<id_product><![CDATA[109092]]></id_product>
<position><![CDATA[108655]]></position>
</category_product>
<category_product><id_category><![CDATA[2]]></id_category>
<id_product><![CDATA[109093]]></id_product>
<position><![CDATA[108656]]></position>
</category_product>
<category_product><id_category><![CDATA[2]]></id_category>
<id_product><![CDATA[109094]]></id_product>
<position><![CDATA[108657]]></position>
</category_product>
<category_product><id_category><![CDATA[2]]></id_category>
<id_product><![CDATA[109095]]></id_product>
<position><![CDATA[108658]]></position>
</category_product>
<category_product><id_category><![CDATA[2]]></id_category>
<id_product><![CDATA[109096]]></id_product>
<position><![CDATA[108659]]></position>
</category_product>
<category_product><id_category><![CDATA[2]]></id_category>
<id_product><![CDATA[109097]]></id_product>
<position><![CDATA[108660]]></position>
</category_product>
<category_product><id_category><![CDATA[2]]></id_category>
<id_product><![CDATA[109098]]></id_product>
<position><![CDATA[108661]]></position>
</category_product>
<category_product><id_category><![CDATA[2]]></id_category>
<id_product><![CDATA[109099]]></id_product>
<position><![CDATA[108662]]></position>
</category_product>
<category_product><id_category><![CDATA[2]]></id_category>
<id_product><![CDATA[109100]]></id_product>
<position><![CDATA[108663]]></position>
</category_product>
<category_product><id_category><![CDATA[2]]></id_category>
<id_product><![CDATA[109101]]></id_product>
<position><![CDATA[108664]]></position>
</category_product>
<category_product><id_category><![CDATA[2]]></id_category>
<id_product><![CDATA[109102]]></id_product>
<position><![CDATA[108665]]></position>
</category_product>
<category_product><id_category><![CDATA[2]]></id_category>
<id_product><![CDATA[109103]]></id_product>
<position><![CDATA[108666]]></position>
</category_product>
<category_product><id_category><![CDATA[2]]></id_category>
<id_product><![CDATA[109104]]></id_product>
<position><![CDATA[108667]]></position>
</category_product>
<category_product><id_category><![CDATA[2]]></id_category>
<id_product><![CDATA[109105]]></id_product>
<position><![CDATA[108668]]></position>
</category_product>
<category_product><id_category><![CDATA[2]]></id_category>
<id_product><![CDATA[109106]]></id_product>
<position><![CDATA[108669]]></position>
</category_product>
<category_product><id_category><![CDATA[2]]></id_category>
<id_product><![CDATA[109107]]></id_product>
<position><![CDATA[108670]]></position>
</category_product>
<category_product><id_category><![CDATA[2]]></id_category>
<id_product><![CDATA[109108]]></id_product>
<position><![CDATA[108671]]></position>
</category_product>
<category_product><id_category><![CDATA[2]]></id_category>
<id_product><![CDATA[109109]]></id_product>
<position><![CDATA[108672]]></position>
</category_product>
<category_product><id_category><![CDATA[2]]></id_category>
<id_product><![CDATA[109110]]></id_product>
<position><![CDATA[108673]]></position>
</category_product>
<category_product><id_category><![CDATA[2]]></id_category>
<id_product><![CDATA[109111]]></id_product>
<position><![CDATA[108674]]></position>
</category_product>
<category_product><id_category><![CDATA[2]]></id_category>
<id_product><![CDATA[109112]]></id_product>
<position><![CDATA[108675]]></position>
</category_product>
<category_product><id_category><![CDATA[2]]></id_category>
<id_product><![CDATA[109113]]></id_product>
<position><![CDATA[108676]]></position>
</category_product>
<category_product><id_category><![CDATA[2]]></id_category>
<id_product><![CDATA[109114]]></id_product>
<position><![CDATA[108677]]></position>
</category_product>
<category_product><id_category><![CDATA[2]]></id_category>
<id_product><![CDATA[109115]]></id_product>
<position><![CDATA[108678]]></position>
</category_product>
<category_product><id_category><![CDATA[2]]></id_category>
<id_product><![CDATA[109116]]></id_product>
<position><![CDATA[108679]]></position>
</category_product>
<category_product><id_category><![CDATA[2]]></id_category>
<id_product><![CDATA[109117]]></id_product>
<position><![CDATA[108680]]></position>
</category_product>
<category_product><id_category><![CDATA[2]]></id_category>
<id_product><![CDATA[109118]]></id_product>
<position><![CDATA[108681]]></position>
</category_product>
<category_product><id_category><![CDATA[2]]></id_category>
<id_product><![CDATA[109119]]></id_product>
<position><![CDATA[108682]]></position>
</category_product>
<category_product><id_category><![CDATA[2]]></id_category>
<id_product><![CDATA[109120]]></id_product>
<position><![CDATA[108683]]></position>
</category_product>
<category_product><id_category><![CDATA[2]]></id_category>
<id_product><![CDATA[109121]]></id_product>
<position><![CDATA[108684]]></position>
</category_product>
<category_product><id_category><![CDATA[2]]></id_category>
<id_product><![CDATA[109122]]></id_product>
<position><![CDATA[108685]]></position>
</category_product>
<category_product><id_category><![CDATA[2]]></id_category>
<id_product><![CDATA[109123]]></id_product>
<position><![CDATA[108686]]></position>
</category_product>
<category_product><id_category><![CDATA[2]]></id_category>
<id_product><![CDATA[109124]]></id_product>
<position><![CDATA[108687]]></position>
</category_product>
<category_product><id_category><![CDATA[2]]></id_category>
<id_product><![CDATA[109125]]></id_product>
<position><![CDATA[108688]]></position>
</category_product>
<category_product><id_category><![CDATA[2]]></id_category>
<id_product><![CDATA[109126]]></id_product>
<position><![CDATA[108689]]></position>
</category_product>
<category_product><id_category><![CDATA[2]]></id_category>
<id_product><![CDATA[109127]]></id_product>
<position><![CDATA[108690]]></position>
</category_product>
<category_product><id_category><![CDATA[2]]></id_category>
<id_product><![CDATA[109128]]></id_product>
<position><![CDATA[108691]]></position>
</category_product>
<category_product><id_category><![CDATA[2]]></id_category>
<id_product><![CDATA[109129]]></id_product>
<position><![CDATA[108692]]></position>
</category_product>
<category_product><id_category><![CDATA[2]]></id_category>
<id_product><![CDATA[109130]]></id_product>
<position><![CDATA[108693]]></position>
</category_product>
<category_product><id_category><![CDATA[2]]></id_category>
<id_product><![CDATA[109131]]></id_product>
<position><![CDATA[108694]]></position>
</category_product>
<category_product><id_category><![CDATA[2]]></id_category>
<id_product><![CDATA[109132]]></id_product>
<position><![CDATA[108695]]></position>
</category_product>
<category_product><id_category><![CDATA[2]]></id_category>
<id_product><![CDATA[109133]]></id_product>
<position><![CDATA[108696]]></position>
</category_product>
<category_product><id_category><![CDATA[2]]></id_category>
<id_product><![CDATA[109134]]></id_product>
<position><![CDATA[108697]]></position>
</category_product>
<category_product><id_category><![CDATA[2]]></id_category>
<id_product><![CDATA[109135]]></id_product>
<position><![CDATA[108698]]></position>
</category_product>
<category_product><id_category><![CDATA[2]]></id_category>
<id_product><![CDATA[109136]]></id_product>
<position><![CDATA[108699]]></position>
</category_product>
<category_product><id_category><![CDATA[2]]></id_category>
<id_product><![CDATA[109137]]></id_product>
<position><![CDATA[108700]]></position>
</category_product>
<category_product><id_category><![CDATA[2]]></id_category>
<id_product><![CDATA[109138]]></id_product>
<position><![CDATA[108701]]></position>
</category_product>
<category_product><id_category><![CDATA[2]]></id_category>
<id_product><![CDATA[109139]]></id_product>
<position><![CDATA[108702]]></position>
</category_product>
<category_product><id_category><![CDATA[2]]></id_category>
<id_product><![CDATA[109140]]></id_product>
<position><![CDATA[108703]]></position>
</category_product>
<category_product><id_category><![CDATA[2]]></id_category>
<id_product><![CDATA[109141]]></id_product>
<position><![CDATA[108704]]></position>
</category_product>
<category_product><id_category><![CDATA[2]]></id_category>
<id_product><![CDATA[109142]]></id_product>
<position><![CDATA[108705]]></position>
</category_product>
<category_product><id_category><![CDATA[2]]></id_category>
<id_product><![CDATA[109143]]></id_product>
<position><![CDATA[108706]]></position>
</category_product>
<category_product><id_category><![CDATA[2]]></id_category>
<id_product><![CDATA[109144]]></id_product>
<position><![CDATA[108707]]></position>
</category_product>
<category_product><id_category><![CDATA[2]]></id_category>
<id_product><![CDATA[109145]]></id_product>
<position><![CDATA[108708]]></position>
</category_product>
<category_product><id_category><![CDATA[2]]></id_category>
<id_product><![CDATA[109146]]></id_product>
<position><![CDATA[108709]]></position>
</category_product>
<category_product><id_category><![CDATA[2]]></id_category>
<id_product><![CDATA[109147]]></id_product>
<position><![CDATA[108710]]></position>
</category_product>
<category_product><id_category><![CDATA[2]]></id_category>
<id_product><![CDATA[109148]]></id_product>
<position><![CDATA[108711]]></position>
</category_product>
<category_product><id_category><![CDATA[2]]></id_category>
<id_product><![CDATA[109149]]></id_product>
<position><![CDATA[108712]]></position>
</category_product>
<category_product><id_category><![CDATA[2]]></id_category>
<id_product><![CDATA[109150]]></id_product>
<position><![CDATA[108713]]></position>
</category_product>
<category_product><id_category><![CDATA[2]]></id_category>
<id_product><![CDATA[109151]]></id_product>
<position><![CDATA[108714]]></position>
</category_product>
<category_product><id_category><![CDATA[2]]></id_category>
<id_product><![CDATA[109152]]></id_product>
<position><![CDATA[108715]]></position>
</category_product>
<category_product><id_category><![CDATA[2]]></id_category>
<id_product><![CDATA[109153]]></id_product>
<position><![CDATA[108716]]></position>
</category_product>
<category_product><id_category><![CDATA[2]]></id_category>
<id_product><![CDATA[109154]]></id_product>
<position><![CDATA[108717]]></position>
</category_product>
<category_product><id_category><![CDATA[2]]></id_category>
<id_product><![CDATA[109155]]></id_product>
<position><![CDATA[108718]]></position>
</category_product>
<category_product><id_category><![CDATA[2]]></id_category>
<id_product><![CDATA[109156]]></id_product>
<position><![CDATA[108719]]></position>
</category_product>
<category_product><id_category><![CDATA[2]]></id_category>
<id_product><![CDATA[109157]]></id_product>
<position><![CDATA[108720]]></position>
</category_product>
<category_product><id_category><![CDATA[2]]></id_category>
<id_product><![CDATA[109158]]></id_product>
<position><![CDATA[108721]]></position>
</category_product>
<category_product><id_category><![CDATA[2]]></id_category>
<id_product><![CDATA[109159]]></id_product>
<position><![CDATA[108722]]></position>
</category_product>
<category_product><id_category><![CDATA[2]]></id_category>
<id_product><![CDATA[109160]]></id_product>
<position><![CDATA[108723]]></position>
</category_product>
<category_product><id_category><![CDATA[2]]></id_category>
<id_product><![CDATA[109161]]></id_product>
<position><![CDATA[108724]]></position>
</category_product>
<category_product><id_category><![CDATA[2]]></id_category>
<id_product><![CDATA[109162]]></id_product>
<position><![CDATA[108725]]></position>
</category_product>
<category_product><id_category><![CDATA[2]]></id_category>
<id_product><![CDATA[109163]]></id_product>
<position><![CDATA[108726]]></position>
</category_product>
<category_product><id_category><![CDATA[2]]></id_category>
<id_product><![CDATA[109164]]></id_product>
<position><![CDATA[108727]]></position>
</category_product>
<category_product><id_category><![CDATA[2]]></id_category>
<id_product><![CDATA[109165]]></id_product>
<position><![CDATA[108728]]></position>
</category_product>
<category_product><id_category><![CDATA[2]]></id_category>
<id_product><![CDATA[109166]]></id_product>
<position><![CDATA[108729]]></position>
</category_product>
<category_product><id_category><![CDATA[2]]></id_category>
<id_product><![CDATA[109167]]></id_product>
<position><![CDATA[108730]]></position>
</category_product>
<category_product><id_category><![CDATA[2]]></id_category>
<id_product><![CDATA[109168]]></id_product>
<position><![CDATA[108731]]></position>
</category_product>
<category_product><id_category><![CDATA[2]]></id_category>
<id_product><![CDATA[109169]]></id_product>
<position><![CDATA[108732]]></position>
</category_product>
<category_product><id_category><![CDATA[2]]></id_category>
<id_product><![CDATA[109170]]></id_product>
<position><![CDATA[108733]]></position>
</category_product>
<category_product><id_category><![CDATA[2]]></id_category>
<id_product><![CDATA[109171]]></id_product>
<position><![CDATA[108734]]></position>
</category_product>
<category_product><id_category><![CDATA[2]]></id_category>
<id_product><![CDATA[109172]]></id_product>
<position><![CDATA[108735]]></position>
</category_product>
<category_product><id_category><![CDATA[2]]></id_category>
<id_product><![CDATA[109173]]></id_product>
<position><![CDATA[108736]]></position>
</category_product>
<category_product><id_category><![CDATA[2]]></id_category>
<id_product><![CDATA[109174]]></id_product>
<position><![CDATA[108737]]></position>
</category_product>
<category_product><id_category><![CDATA[2]]></id_category>
<id_product><![CDATA[109175]]></id_product>
<position><![CDATA[108738]]></position>
</category_product>
<category_product><id_category><![CDATA[2]]></id_category>
<id_product><![CDATA[109176]]></id_product>
<position><![CDATA[108739]]></position>
</category_product>
<category_product><id_category><![CDATA[2]]></id_category>
<id_product><![CDATA[109177]]></id_product>
<position><![CDATA[108740]]></position>
</category_product>
<category_product><id_category><![CDATA[2]]></id_category>
<id_product><![CDATA[109178]]></id_product>
<position><![CDATA[108741]]></position>
</category_product>
<category_product><id_category><![CDATA[2]]></id_category>
<id_product><![CDATA[109179]]></id_product>
<position><![CDATA[108742]]></position>
</category_product>
<category_product><id_category><![CDATA[2]]></id_category>
<id_product><![CDATA[109180]]></id_product>
<position><![CDATA[108743]]></position>
</category_product>
<category_product><id_category><![CDATA[2]]></id_category>
<id_product><![CDATA[109181]]></id_product>
<position><![CDATA[108744]]></position>
</category_product>
<category_product><id_category><![CDATA[2]]></id_category>
<id_product><![CDATA[109182]]></id_product>
<position><![CDATA[108745]]></position>
</category_product>
<category_product><id_category><![CDATA[2]]></id_category>
<id_product><![CDATA[109183]]></id_product>
<position><![CDATA[108746]]></position>
</category_product>
<category_product><id_category><![CDATA[2]]></id_category>
<id_product><![CDATA[109184]]></id_product>
<position><![CDATA[108747]]></position>
</category_product>
<category_product><id_category><![CDATA[2]]></id_category>
<id_product><![CDATA[109185]]></id_product>
<position><![CDATA[108748]]></position>
</category_product>
<category_product><id_category><![CDATA[2]]></id_category>
<id_product><![CDATA[109186]]></id_product>
<position><![CDATA[108749]]></position>
</category_product>
<category_product><id_category><![CDATA[2]]></id_category>
<id_product><![CDATA[109187]]></id_product>
<position><![CDATA[108750]]></position>
</category_product>
<category_product><id_category><![CDATA[2]]></id_category>
<id_product><![CDATA[109188]]></id_product>
<position><![CDATA[108751]]></position>
</category_product>
<category_product><id_category><![CDATA[2]]></id_category>
<id_product><![CDATA[109189]]></id_product>
<position><![CDATA[108752]]></position>
</category_product>
<category_product><id_category><![CDATA[2]]></id_category>
<id_product><![CDATA[109190]]></id_product>
<position><![CDATA[108753]]></position>
</category_product>
<category_product><id_category><![CDATA[2]]></id_category>
<id_product><![CDATA[109191]]></id_product>
<position><![CDATA[108754]]></position>
</category_product>
<category_product><id_category><![CDATA[2]]></id_category>
<id_product><![CDATA[109192]]></id_product>
<position><![CDATA[108755]]></position>
</category_product>
<category_product><id_category><![CDATA[2]]></id_category>
<id_product><![CDATA[109193]]></id_product>
<position><![CDATA[108756]]></position>
</category_product>
<category_product><id_category><![CDATA[2]]></id_category>
<id_product><![CDATA[109194]]></id_product>
<position><![CDATA[108757]]></position>
</category_product>
<category_product><id_category><![CDATA[2]]></id_category>
<id_product><![CDATA[109195]]></id_product>
<position><![CDATA[108758]]></position>
</category_product>
<category_product><id_category><![CDATA[2]]></id_category>
<id_product><![CDATA[109196]]></id_product>
<position><![CDATA[108759]]></position>
</category_product>
<category_product><id_category><![CDATA[2]]></id_category>
<id_product><![CDATA[109197]]></id_product>
<position><![CDATA[108760]]></position>
</category_product>
<category_product><id_category><![CDATA[2]]></id_category>
<id_product><![CDATA[109198]]></id_product>
<position><![CDATA[108761]]></position>
</category_product>
<category_product><id_category><![CDATA[2]]></id_category>
<id_product><![CDATA[109199]]></id_product>
<position><![CDATA[108762]]></position>
</category_product>
<category_product><id_category><![CDATA[2]]></id_category>
<id_product><![CDATA[109200]]></id_product>
<position><![CDATA[108763]]></position>
</category_product>
<category_product><id_category><![CDATA[2]]></id_category>
<id_product><![CDATA[109201]]></id_product>
<position><![CDATA[108764]]></position>
</category_product>
<category_product><id_category><![CDATA[2]]></id_category>
<id_product><![CDATA[109202]]></id_product>
<position><![CDATA[108765]]></position>
</category_product>
<category_product><id_category><![CDATA[2]]></id_category>
<id_product><![CDATA[109203]]></id_product>
<position><![CDATA[108766]]></position>
</category_product>
<category_product><id_category><![CDATA[2]]></id_category>
<id_product><![CDATA[109204]]></id_product>
<position><![CDATA[108767]]></position>
</category_product>
<category_product><id_category><![CDATA[2]]></id_category>
<id_product><![CDATA[109205]]></id_product>
<position><![CDATA[108768]]></position>
</category_product>
<category_product><id_category><![CDATA[2]]></id_category>
<id_product><![CDATA[109206]]></id_product>
<position><![CDATA[108769]]></position>
</category_product>
<category_product><id_category><![CDATA[2]]></id_category>
<id_product><![CDATA[109207]]></id_product>
<position><![CDATA[108770]]></position>
</category_product>
<category_product><id_category><![CDATA[2]]></id_category>
<id_product><![CDATA[109208]]></id_product>
<position><![CDATA[108771]]></position>
</category_product>
<category_product><id_category><![CDATA[2]]></id_category>
<id_product><![CDATA[109209]]></id_product>
<position><![CDATA[108772]]></position>
</category_product>
<category_product><id_category><![CDATA[2]]></id_category>
<id_product><![CDATA[109210]]></id_product>
<position><![CDATA[108773]]></position>
</category_product>
<category_product><id_category><![CDATA[2]]></id_category>
<id_product><![CDATA[109211]]></id_product>
<position><![CDATA[108774]]></position>
</category_product>
<category_product><id_category><![CDATA[2]]></id_category>
<id_product><![CDATA[109212]]></id_product>
<position><![CDATA[108775]]></position>
</category_product>
<category_product><id_category><![CDATA[2]]></id_category>
<id_product><![CDATA[109213]]></id_product>
<position><![CDATA[108776]]></position>
</category_product>
<category_product><id_category><![CDATA[2]]></id_category>
<id_product><![CDATA[109214]]></id_product>
<position><![CDATA[108777]]></position>
</category_product>
<category_product><id_category><![CDATA[2]]></id_category>
<id_product><![CDATA[109215]]></id_product>
<position><![CDATA[108778]]></position>
</category_product>
<category_product><id_category><![CDATA[2]]></id_category>
<id_product><![CDATA[109216]]></id_product>
<position><![CDATA[108779]]></position>
</category_product>
<category_product><id_category><![CDATA[2]]></id_category>
<id_product><![CDATA[109217]]></id_product>
<position><![CDATA[108780]]></position>
</category_product>
<category_product><id_category><![CDATA[2]]></id_category>
<id_product><![CDATA[109218]]></id_product>
<position><![CDATA[108781]]></position>
</category_product>
<category_product><id_category><![CDATA[2]]></id_category>
<id_product><![CDATA[109219]]></id_product>
<position><![CDATA[108782]]></position>
</category_product>
<category_product><id_category><![CDATA[2]]></id_category>
<id_product><![CDATA[109220]]></id_product>
<position><![CDATA[108783]]></position>
</category_product>
<category_product><id_category><![CDATA[2]]></id_category>
<id_product><![CDATA[109221]]></id_product>
<position><![CDATA[108784]]></position>
</category_product>
<category_product><id_category><![CDATA[2]]></id_category>
<id_product><![CDATA[109222]]></id_product>
<position><![CDATA[108785]]></position>
</category_product>
<category_product><id_category><![CDATA[2]]></id_category>
<id_product><![CDATA[109223]]></id_product>
<position><![CDATA[108786]]></position>
</category_product>
<category_product><id_category><![CDATA[2]]></id_category>
<id_product><![CDATA[109224]]></id_product>
<position><![CDATA[108787]]></position>
</category_product>
<category_product><id_category><![CDATA[2]]></id_category>
<id_product><![CDATA[109225]]></id_product>
<position><![CDATA[108788]]></position>
</category_product>
<category_product><id_category><![CDATA[2]]></id_category>
<id_product><![CDATA[109226]]></id_product>
<position><![CDATA[108789]]></position>
</category_product>
<category_product><id_category><![CDATA[2]]></id_category>
<id_product><![CDATA[109227]]></id_product>
<position><![CDATA[108790]]></position>
</category_product>
<category_product><id_category><![CDATA[2]]></id_category>
<id_product><![CDATA[109228]]></id_product>
<position><![CDATA[108791]]></position>
</category_product>
<category_product><id_category><![CDATA[2]]></id_category>
<id_product><![CDATA[109229]]></id_product>
<position><![CDATA[108792]]></position>
</category_product>
<category_product><id_category><![CDATA[2]]></id_category>
<id_product><![CDATA[109230]]></id_product>
<position><![CDATA[108793]]></position>
</category_product>
<category_product><id_category><![CDATA[2]]></id_category>
<id_product><![CDATA[109231]]></id_product>
<position><![CDATA[108794]]></position>
</category_product>
<category_product><id_category><![CDATA[2]]></id_category>
<id_product><![CDATA[109232]]></id_product>
<position><![CDATA[108795]]></position>
</category_product>
<category_product><id_category><![CDATA[2]]></id_category>
<id_product><![CDATA[109233]]></id_product>
<position><![CDATA[108796]]></position>
</category_product>
<category_product><id_category><![CDATA[2]]></id_category>
<id_product><![CDATA[109234]]></id_product>
<position><![CDATA[108797]]></position>
</category_product>
<category_product><id_category><![CDATA[2]]></id_category>
<id_product><![CDATA[109235]]></id_product>
<position><![CDATA[108798]]></position>
</category_product>
<category_product><id_category><![CDATA[2]]></id_category>
<id_product><![CDATA[109236]]></id_product>
<position><![CDATA[108799]]></position>
</category_product>
<category_product><id_category><![CDATA[2]]></id_category>
<id_product><![CDATA[109237]]></id_product>
<position><![CDATA[108800]]></position>
</category_product>
<category_product><id_category><![CDATA[2]]></id_category>
<id_product><![CDATA[109238]]></id_product>
<position><![CDATA[108801]]></position>
</category_product>
<category_product><id_category><![CDATA[2]]></id_category>
<id_product><![CDATA[109239]]></id_product>
<position><![CDATA[108802]]></position>
</category_product>
<category_product><id_category><![CDATA[2]]></id_category>
<id_product><![CDATA[109240]]></id_product>
<position><![CDATA[108803]]></position>
</category_product>
<category_product><id_category><![CDATA[2]]></id_category>
<id_product><![CDATA[109241]]></id_product>
<position><![CDATA[108804]]></position>
</category_product>
<category_product><id_category><![CDATA[2]]></id_category>
<id_product><![CDATA[109242]]></id_product>
<position><![CDATA[108805]]></position>
</category_product>
<category_product><id_category><![CDATA[2]]></id_category>
<id_product><![CDATA[109243]]></id_product>
<position><![CDATA[108806]]></position>
</category_product>
<category_product><id_category><![CDATA[2]]></id_category>
<id_product><![CDATA[109244]]></id_product>
<position><![CDATA[108807]]></position>
</category_product>
<category_product><id_category><![CDATA[2]]></id_category>
<id_product><![CDATA[109245]]></id_product>
<position><![CDATA[108808]]></position>
</category_product>
<category_product><id_category><![CDATA[2]]></id_category>
<id_product><![CDATA[109246]]></id_product>
<position><![CDATA[108809]]></position>
</category_product>
<category_product><id_category><![CDATA[2]]></id_category>
<id_product><![CDATA[109247]]></id_product>
<position><![CDATA[108810]]></position>
</category_product>
<category_product><id_category><![CDATA[2]]></id_category>
<id_product><![CDATA[109248]]></id_product>
<position><![CDATA[108811]]></position>
</category_product>
<category_product><id_category><![CDATA[2]]></id_category>
<id_product><![CDATA[109249]]></id_product>
<position><![CDATA[108812]]></position>
</category_product>
<category_product><id_category><![CDATA[2]]></id_category>
<id_product><![CDATA[109250]]></id_product>
<position><![CDATA[108813]]></position>
</category_product>
<category_product><id_category><![CDATA[2]]></id_category>
<id_product><![CDATA[109251]]></id_product>
<position><![CDATA[108814]]></position>
</category_product>
<category_product><id_category><![CDATA[2]]></id_category>
<id_product><![CDATA[109252]]></id_product>
<position><![CDATA[108815]]></position>
</category_product>
<category_product><id_category><![CDATA[2]]></id_category>
<id_product><![CDATA[109253]]></id_product>
<position><![CDATA[108816]]></position>
</category_product>
<category_product><id_category><![CDATA[2]]></id_category>
<id_product><![CDATA[109254]]></id_product>
<position><![CDATA[108817]]></position>
</category_product>
<category_product><id_category><![CDATA[2]]></id_category>
<id_product><![CDATA[109255]]></id_product>
<position><![CDATA[108818]]></position>
</category_product>
<category_product><id_category><![CDATA[2]]></id_category>
<id_product><![CDATA[109256]]></id_product>
<position><![CDATA[108819]]></position>
</category_product>
<category_product><id_category><![CDATA[2]]></id_category>
<id_product><![CDATA[109257]]></id_product>
<position><![CDATA[108820]]></position>
</category_product>
<category_product><id_category><![CDATA[2]]></id_category>
<id_product><![CDATA[109258]]></id_product>
<position><![CDATA[108821]]></position>
</category_product>
<category_product><id_category><![CDATA[2]]></id_category>
<id_product><![CDATA[109259]]></id_product>
<position><![CDATA[108822]]></position>
</category_product>
<category_product><id_category><![CDATA[2]]></id_category>
<id_product><![CDATA[109260]]></id_product>
<position><![CDATA[108823]]></position>
</category_product>
<category_product><id_category><![CDATA[2]]></id_category>
<id_product><![CDATA[109261]]></id_product>
<position><![CDATA[108824]]></position>
</category_product>
<category_product><id_category><![CDATA[2]]></id_category>
<id_product><![CDATA[109262]]></id_product>
<position><![CDATA[108825]]></position>
</category_product>
<category_product><id_category><![CDATA[2]]></id_category>
<id_product><![CDATA[109263]]></id_product>
<position><![CDATA[108826]]></position>
</category_product>
<category_product><id_category><![CDATA[2]]></id_category>
<id_product><![CDATA[109264]]></id_product>
<position><![CDATA[108827]]></position>
</category_product>
<category_product><id_category><![CDATA[2]]></id_category>
<id_product><![CDATA[109265]]></id_product>
<position><![CDATA[108828]]></position>
</category_product>
<category_product><id_category><![CDATA[2]]></id_category>
<id_product><![CDATA[109266]]></id_product>
<position><![CDATA[108829]]></position>
</category_product>
<category_product><id_category><![CDATA[2]]></id_category>
<id_product><![CDATA[109267]]></id_product>
<position><![CDATA[108830]]></position>
</category_product>
<category_product><id_category><![CDATA[2]]></id_category>
<id_product><![CDATA[109268]]></id_product>
<position><![CDATA[108831]]></position>
</category_product>
<category_product><id_category><![CDATA[2]]></id_category>
<id_product><![CDATA[109269]]></id_product>
<position><![CDATA[108832]]></position>
</category_product>
<category_product><id_category><![CDATA[2]]></id_category>
<id_product><![CDATA[109270]]></id_product>
<position><![CDATA[108833]]></position>
</category_product>
<category_product><id_category><![CDATA[2]]></id_category>
<id_product><![CDATA[109271]]></id_product>
<position><![CDATA[108834]]></position>
</category_product>
<category_product><id_category><![CDATA[2]]></id_category>
<id_product><![CDATA[109272]]></id_product>
<position><![CDATA[108835]]></position>
</category_product>
<category_product><id_category><![CDATA[2]]></id_category>
<id_product><![CDATA[109273]]></id_product>
<position><![CDATA[108836]]></position>
</category_product>
<category_product><id_category><![CDATA[2]]></id_category>
<id_product><![CDATA[109274]]></id_product>
<position><![CDATA[108837]]></position>
</category_product>
<category_product><id_category><![CDATA[2]]></id_category>
<id_product><![CDATA[109275]]></id_product>
<position><![CDATA[108838]]></position>
</category_product>
<category_product><id_category><![CDATA[2]]></id_category>
<id_product><![CDATA[109276]]></id_product>
<position><![CDATA[108839]]></position>
</category_product>
<category_product><id_category><![CDATA[2]]></id_category>
<id_product><![CDATA[109277]]></id_product>
<position><![CDATA[108840]]></position>
</category_product>
<category_product><id_category><![CDATA[2]]></id_category>
<id_product><![CDATA[109278]]></id_product>
<position><![CDATA[108841]]></position>
</category_product>
<category_product><id_category><![CDATA[2]]></id_category>
<id_product><![CDATA[109279]]></id_product>
<position><![CDATA[108842]]></position>
</category_product>
<category_product><id_category><![CDATA[2]]></id_category>
<id_product><![CDATA[109280]]></id_product>
<position><![CDATA[108843]]></position>
</category_product>
<category_product><id_category><![CDATA[2]]></id_category>
<id_product><![CDATA[109281]]></id_product>
<position><![CDATA[108844]]></position>
</category_product>
<category_product><id_category><![CDATA[2]]></id_category>
<id_product><![CDATA[109282]]></id_product>
<position><![CDATA[108845]]></position>
</category_product>
<category_product><id_category><![CDATA[2]]></id_category>
<id_product><![CDATA[109283]]></id_product>
<position><![CDATA[108846]]></position>
</category_product>
<category_product><id_category><![CDATA[2]]></id_category>
<id_product><![CDATA[109284]]></id_product>
<position><![CDATA[108847]]></position>
</category_product>
<category_product><id_category><![CDATA[2]]></id_category>
<id_product><![CDATA[109285]]></id_product>
<position><![CDATA[108848]]></position>
</category_product>
<category_product><id_category><![CDATA[2]]></id_category>
<id_product><![CDATA[109286]]></id_product>
<position><![CDATA[108849]]></position>
</category_product>
<category_product><id_category><![CDATA[2]]></id_category>
<id_product><![CDATA[109287]]></id_product>
<position><![CDATA[108850]]></position>
</category_product>
<category_product><id_category><![CDATA[2]]></id_category>
<id_product><![CDATA[109288]]></id_product>
<position><![CDATA[108851]]></position>
</category_product>
<category_product><id_category><![CDATA[2]]></id_category>
<id_product><![CDATA[109289]]></id_product>
<position><![CDATA[108852]]></position>
</category_product>
<category_product><id_category><![CDATA[2]]></id_category>
<id_product><![CDATA[109290]]></id_product>
<position><![CDATA[108853]]></position>
</category_product>
<category_product><id_category><![CDATA[2]]></id_category>
<id_product><![CDATA[109291]]></id_product>
<position><![CDATA[108854]]></position>
</category_product>
<category_product><id_category><![CDATA[2]]></id_category>
<id_product><![CDATA[109292]]></id_product>
<position><![CDATA[108855]]></position>
</category_product>
<category_product><id_category><![CDATA[2]]></id_category>
<id_product><![CDATA[109293]]></id_product>
<position><![CDATA[108856]]></position>
</category_product>
<category_product><id_category><![CDATA[2]]></id_category>
<id_product><![CDATA[109294]]></id_product>
<position><![CDATA[108857]]></position>
</category_product>
<category_product><id_category><![CDATA[2]]></id_category>
<id_product><![CDATA[109295]]></id_product>
<position><![CDATA[108858]]></position>
</category_product>
<category_product><id_category><![CDATA[2]]></id_category>
<id_product><![CDATA[109296]]></id_product>
<position><![CDATA[108859]]></position>
</category_product>
<category_product><id_category><![CDATA[2]]></id_category>
<id_product><![CDATA[109297]]></id_product>
<position><![CDATA[108860]]></position>
</category_product>
<category_product><id_category><![CDATA[2]]></id_category>
<id_product><![CDATA[109298]]></id_product>
<position><![CDATA[108861]]></position>
</category_product>
<category_product><id_category><![CDATA[2]]></id_category>
<id_product><![CDATA[109299]]></id_product>
<position><![CDATA[108862]]></position>
</category_product>
<category_product><id_category><![CDATA[2]]></id_category>
<id_product><![CDATA[109300]]></id_product>
<position><![CDATA[108863]]></position>
</category_product>
<category_product><id_category><![CDATA[2]]></id_category>
<id_product><![CDATA[109301]]></id_product>
<position><![CDATA[108864]]></position>
</category_product>
<category_product><id_category><![CDATA[2]]></id_category>
<id_product><![CDATA[109302]]></id_product>
<position><![CDATA[108865]]></position>
</category_product>
<category_product><id_category><![CDATA[2]]></id_category>
<id_product><![CDATA[109303]]></id_product>
<position><![CDATA[108866]]></position>
</category_product>
<category_product><id_category><![CDATA[2]]></id_category>
<id_product><![CDATA[109304]]></id_product>
<position><![CDATA[108867]]></position>
</category_product>
<category_product><id_category><![CDATA[2]]></id_category>
<id_product><![CDATA[109305]]></id_product>
<position><![CDATA[108868]]></position>
</category_product>
<category_product><id_category><![CDATA[2]]></id_category>
<id_product><![CDATA[109306]]></id_product>
<position><![CDATA[108869]]></position>
</category_product>
<category_product><id_category><![CDATA[2]]></id_category>
<id_product><![CDATA[109307]]></id_product>
<position><![CDATA[108870]]></position>
</category_product>
<category_product><id_category><![CDATA[2]]></id_category>
<id_product><![CDATA[109308]]></id_product>
<position><![CDATA[108871]]></position>
</category_product>
<category_product><id_category><![CDATA[2]]></id_category>
<id_product><![CDATA[109309]]></id_product>
<position><![CDATA[108872]]></position>
</category_product>
<category_product><id_category><![CDATA[2]]></id_category>
<id_product><![CDATA[109310]]></id_product>
<position><![CDATA[108873]]></position>
</category_product>
<category_product><id_category><![CDATA[2]]></id_category>
<id_product><![CDATA[109311]]></id_product>
<position><![CDATA[108874]]></position>
</category_product>
<category_product><id_category><![CDATA[2]]></id_category>
<id_product><![CDATA[109312]]></id_product>
<position><![CDATA[108875]]></position>
</category_product>
<category_product><id_category><![CDATA[2]]></id_category>
<id_product><![CDATA[109313]]></id_product>
<position><![CDATA[108876]]></position>
</category_product>
<category_product><id_category><![CDATA[2]]></id_category>
<id_product><![CDATA[109314]]></id_product>
<position><![CDATA[108877]]></position>
</category_product>
<category_product><id_category><![CDATA[2]]></id_category>
<id_product><![CDATA[109315]]></id_product>
<position><![CDATA[108878]]></position>
</category_product>
<category_product><id_category><![CDATA[2]]></id_category>
<id_product><![CDATA[109316]]></id_product>
<position><![CDATA[108879]]></position>
</category_product>
<category_product><id_category><![CDATA[2]]></id_category>
<id_product><![CDATA[109317]]></id_product>
<position><![CDATA[108880]]></position>
</category_product>
<category_product><id_category><![CDATA[2]]></id_category>
<id_product><![CDATA[109318]]></id_product>
<position><![CDATA[108881]]></position>
</category_product>
<category_product><id_category><![CDATA[2]]></id_category>
<id_product><![CDATA[109319]]></id_product>
<position><![CDATA[108882]]></position>
</category_product>
<category_product><id_category><![CDATA[2]]></id_category>
<id_product><![CDATA[109320]]></id_product>
<position><![CDATA[108883]]></position>
</category_product>
<category_product><id_category><![CDATA[2]]></id_category>
<id_product><![CDATA[109321]]></id_product>
<position><![CDATA[108884]]></position>
</category_product>
<category_product><id_category><![CDATA[2]]></id_category>
<id_product><![CDATA[109322]]></id_product>
<position><![CDATA[108885]]></position>
</category_product>
<category_product><id_category><![CDATA[2]]></id_category>
<id_product><![CDATA[109323]]></id_product>
<position><![CDATA[108886]]></position>
</category_product>
<category_product><id_category><![CDATA[2]]></id_category>
<id_product><![CDATA[109324]]></id_product>
<position><![CDATA[108887]]></position>
</category_product>
<category_product><id_category><![CDATA[2]]></id_category>
<id_product><![CDATA[109325]]></id_product>
<position><![CDATA[108888]]></position>
</category_product>
<category_product><id_category><![CDATA[2]]></id_category>
<id_product><![CDATA[109326]]></id_product>
<position><![CDATA[108889]]></position>
</category_product>
<category_product><id_category><![CDATA[2]]></id_category>
<id_product><![CDATA[109327]]></id_product>
<position><![CDATA[108890]]></position>
</category_product>
<category_product><id_category><![CDATA[2]]></id_category>
<id_product><![CDATA[109328]]></id_product>
<position><![CDATA[108891]]></position>
</category_product>
<category_product><id_category><![CDATA[2]]></id_category>
<id_product><![CDATA[109329]]></id_product>
<position><![CDATA[108892]]></position>
</category_product>
<category_product><id_category><![CDATA[2]]></id_category>
<id_product><![CDATA[109330]]></id_product>
<position><![CDATA[108893]]></position>
</category_product>
<category_product><id_category><![CDATA[2]]></id_category>
<id_product><![CDATA[109331]]></id_product>
<position><![CDATA[108894]]></position>
</category_product>
<category_product><id_category><![CDATA[2]]></id_category>
<id_product><![CDATA[109332]]></id_product>
<position><![CDATA[108895]]></position>
</category_product>
<category_product><id_category><![CDATA[2]]></id_category>
<id_product><![CDATA[109333]]></id_product>
<position><![CDATA[108896]]></position>
</category_product>
<category_product><id_category><![CDATA[2]]></id_category>
<id_product><![CDATA[109334]]></id_product>
<position><![CDATA[108897]]></position>
</category_product>
<category_product><id_category><![CDATA[2]]></id_category>
<id_product><![CDATA[109335]]></id_product>
<position><![CDATA[108898]]></position>
</category_product>
<category_product><id_category><![CDATA[2]]></id_category>
<id_product><![CDATA[109336]]></id_product>
<position><![CDATA[108899]]></position>
</category_product>
<category_product><id_category><![CDATA[2]]></id_category>
<id_product><![CDATA[109337]]></id_product>
<position><![CDATA[108900]]></position>
</category_product>
<category_product><id_category><![CDATA[2]]></id_category>
<id_product><![CDATA[109338]]></id_product>
<position><![CDATA[108901]]></position>
</category_product>
<category_product><id_category><![CDATA[2]]></id_category>
<id_product><![CDATA[109339]]></id_product>
<position><![CDATA[108902]]></position>
</category_product>
<category_product><id_category><![CDATA[2]]></id_category>
<id_product><![CDATA[109340]]></id_product>
<position><![CDATA[108903]]></position>
</category_product>
<category_product><id_category><![CDATA[2]]></id_category>
<id_product><![CDATA[109341]]></id_product>
<position><![CDATA[108904]]></position>
</category_product>
<category_product><id_category><![CDATA[2]]></id_category>
<id_product><![CDATA[109342]]></id_product>
<position><![CDATA[108905]]></position>
</category_product>
<category_product><id_category><![CDATA[2]]></id_category>
<id_product><![CDATA[109343]]></id_product>
<position><![CDATA[108906]]></position>
</category_product>
<category_product><id_category><![CDATA[2]]></id_category>
<id_product><![CDATA[109344]]></id_product>
<position><![CDATA[108907]]></position>
</category_product>
<category_product><id_category><![CDATA[2]]></id_category>
<id_product><![CDATA[109345]]></id_product>
<position><![CDATA[108908]]></position>
</category_product>
<category_product><id_category><![CDATA[2]]></id_category>
<id_product><![CDATA[109346]]></id_product>
<position><![CDATA[108909]]></position>
</category_product>
<category_product><id_category><![CDATA[2]]></id_category>
<id_product><![CDATA[109347]]></id_product>
<position><![CDATA[108910]]></position>
</category_product>
<category_product><id_category><![CDATA[2]]></id_category>
<id_product><![CDATA[109348]]></id_product>
<position><![CDATA[108911]]></position>
</category_product>
<category_product><id_category><![CDATA[2]]></id_category>
<id_product><![CDATA[109349]]></id_product>
<position><![CDATA[108912]]></position>
</category_product>
<category_product><id_category><![CDATA[2]]></id_category>
<id_product><![CDATA[109350]]></id_product>
<position><![CDATA[108913]]></position>
</category_product>
<category_product><id_category><![CDATA[2]]></id_category>
<id_product><![CDATA[109351]]></id_product>
<position><![CDATA[108914]]></position>
</category_product>
<category_product><id_category><![CDATA[2]]></id_category>
<id_product><![CDATA[109352]]></id_product>
<position><![CDATA[108915]]></position>
</category_product>
<category_product><id_category><![CDATA[2]]></id_category>
<id_product><![CDATA[109353]]></id_product>
<position><![CDATA[108916]]></position>
</category_product>
<category_product><id_category><![CDATA[2]]></id_category>
<id_product><![CDATA[109354]]></id_product>
<position><![CDATA[108917]]></position>
</category_product>
<category_product><id_category><![CDATA[2]]></id_category>
<id_product><![CDATA[109355]]></id_product>
<position><![CDATA[108918]]></position>
</category_product>
<category_product><id_category><![CDATA[2]]></id_category>
<id_product><![CDATA[109356]]></id_product>
<position><![CDATA[108919]]></position>
</category_product>
<category_product><id_category><![CDATA[2]]></id_category>
<id_product><![CDATA[109357]]></id_product>
<position><![CDATA[108920]]></position>
</category_product>
<category_product><id_category><![CDATA[2]]></id_category>
<id_product><![CDATA[109358]]></id_product>
<position><![CDATA[108921]]></position>
</category_product>
<category_product><id_category><![CDATA[2]]></id_category>
<id_product><![CDATA[109359]]></id_product>
<position><![CDATA[108922]]></position>
</category_product>
<category_product><id_category><![CDATA[2]]></id_category>
<id_product><![CDATA[109360]]></id_product>
<position><![CDATA[108923]]></position>
</category_product>
<category_product><id_category><![CDATA[2]]></id_category>
<id_product><![CDATA[109361]]></id_product>
<position><![CDATA[108924]]></position>
</category_product>
<category_product><id_category><![CDATA[2]]></id_category>
<id_product><![CDATA[109362]]></id_product>
<position><![CDATA[108925]]></position>
</category_product>
<category_product><id_category><![CDATA[2]]></id_category>
<id_product><![CDATA[109363]]></id_product>
<position><![CDATA[108926]]></position>
</category_product>
<category_product><id_category><![CDATA[2]]></id_category>
<id_product><![CDATA[109364]]></id_product>
<position><![CDATA[108927]]></position>
</category_product>
<category_product><id_category><![CDATA[2]]></id_category>
<id_product><![CDATA[109365]]></id_product>
<position><![CDATA[108928]]></position>
</category_product>
<category_product><id_category><![CDATA[2]]></id_category>
<id_product><![CDATA[109366]]></id_product>
<position><![CDATA[108929]]></position>
</category_product>
<category_product><id_category><![CDATA[2]]></id_category>
<id_product><![CDATA[109367]]></id_product>
<position><![CDATA[108930]]></position>
</category_product>
<category_product><id_category><![CDATA[2]]></id_category>
<id_product><![CDATA[109368]]></id_product>
<position><![CDATA[108931]]></position>
</category_product>
<category_product><id_category><![CDATA[2]]></id_category>
<id_product><![CDATA[109369]]></id_product>
<position><![CDATA[108932]]></position>
</category_product>
<category_product><id_category><![CDATA[2]]></id_category>
<id_product><![CDATA[109370]]></id_product>
<position><![CDATA[108933]]></position>
</category_product>
<category_product><id_category><![CDATA[2]]></id_category>
<id_product><![CDATA[109371]]></id_product>
<position><![CDATA[108934]]></position>
</category_product>
<category_product><id_category><![CDATA[2]]></id_category>
<id_product><![CDATA[109372]]></id_product>
<position><![CDATA[108935]]></position>
</category_product>
<category_product><id_category><![CDATA[2]]></id_category>
<id_product><![CDATA[109373]]></id_product>
<position><![CDATA[108936]]></position>
</category_product>
<category_product><id_category><![CDATA[2]]></id_category>
<id_product><![CDATA[109374]]></id_product>
<position><![CDATA[108937]]></position>
</category_product>
<category_product><id_category><![CDATA[2]]></id_category>
<id_product><![CDATA[109375]]></id_product>
<position><![CDATA[108938]]></position>
</category_product>
<category_product><id_category><![CDATA[2]]></id_category>
<id_product><![CDATA[109376]]></id_product>
<position><![CDATA[108939]]></position>
</category_product>
<category_product><id_category><![CDATA[2]]></id_category>
<id_product><![CDATA[109377]]></id_product>
<position><![CDATA[108940]]></position>
</category_product>
<category_product><id_category><![CDATA[2]]></id_category>
<id_product><![CDATA[109378]]></id_product>
<position><![CDATA[108941]]></position>
</category_product>
<category_product><id_category><![CDATA[2]]></id_category>
<id_product><![CDATA[109379]]></id_product>
<position><![CDATA[108942]]></position>
</category_product>
<category_product><id_category><![CDATA[2]]></id_category>
<id_product><![CDATA[109380]]></id_product>
<position><![CDATA[108943]]></position>
</category_product>
<category_product><id_category><![CDATA[2]]></id_category>
<id_product><![CDATA[109381]]></id_product>
<position><![CDATA[108944]]></position>
</category_product>
<category_product><id_category><![CDATA[2]]></id_category>
<id_product><![CDATA[109382]]></id_product>
<position><![CDATA[108945]]></position>
</category_product>
<category_product><id_category><![CDATA[2]]></id_category>
<id_product><![CDATA[109383]]></id_product>
<position><![CDATA[108946]]></position>
</category_product>
<category_product><id_category><![CDATA[2]]></id_category>
<id_product><![CDATA[109384]]></id_product>
<position><![CDATA[108947]]></position>
</category_product>
<category_product><id_category><![CDATA[2]]></id_category>
<id_product><![CDATA[109385]]></id_product>
<position><![CDATA[108948]]></position>
</category_product>
<category_product><id_category><![CDATA[2]]></id_category>
<id_product><![CDATA[109386]]></id_product>
<position><![CDATA[108949]]></position>
</category_product>
<category_product><id_category><![CDATA[2]]></id_category>
<id_product><![CDATA[109387]]></id_product>
<position><![CDATA[108950]]></position>
</category_product>
<category_product><id_category><![CDATA[2]]></id_category>
<id_product><![CDATA[109388]]></id_product>
<position><![CDATA[108951]]></position>
</category_product>
<category_product><id_category><![CDATA[2]]></id_category>
<id_product><![CDATA[109389]]></id_product>
<position><![CDATA[108952]]></position>
</category_product>
<category_product><id_category><![CDATA[2]]></id_category>
<id_product><![CDATA[109390]]></id_product>
<position><![CDATA[108953]]></position>
</category_product>
<category_product><id_category><![CDATA[2]]></id_category>
<id_product><![CDATA[109391]]></id_product>
<position><![CDATA[108954]]></position>
</category_product>
<category_product><id_category><![CDATA[2]]></id_category>
<id_product><![CDATA[109392]]></id_product>
<position><![CDATA[108955]]></position>
</category_product>
<category_product><id_category><![CDATA[2]]></id_category>
<id_product><![CDATA[109393]]></id_product>
<position><![CDATA[108956]]></position>
</category_product>
<category_product><id_category><![CDATA[2]]></id_category>
<id_product><![CDATA[109394]]></id_product>
<position><![CDATA[108957]]></position>
</category_product>
<category_product><id_category><![CDATA[2]]></id_category>
<id_product><![CDATA[109395]]></id_product>
<position><![CDATA[108958]]></position>
</category_product>
<category_product><id_category><![CDATA[2]]></id_category>
<id_product><![CDATA[109396]]></id_product>
<position><![CDATA[108959]]></position>
</category_product>
<category_product><id_category><![CDATA[2]]></id_category>
<id_product><![CDATA[109397]]></id_product>
<position><![CDATA[108960]]></position>
</category_product>
<category_product><id_category><![CDATA[2]]></id_category>
<id_product><![CDATA[109398]]></id_product>
<position><![CDATA[108961]]></position>
</category_product>
<category_product><id_category><![CDATA[2]]></id_category>
<id_product><![CDATA[109399]]></id_product>
<position><![CDATA[108962]]></position>
</category_product>
<category_product><id_category><![CDATA[2]]></id_category>
<id_product><![CDATA[109400]]></id_product>
<position><![CDATA[108963]]></position>
</category_product>
<category_product><id_category><![CDATA[2]]></id_category>
<id_product><![CDATA[109401]]></id_product>
<position><![CDATA[108964]]></position>
</category_product>
<category_product><id_category><![CDATA[2]]></id_category>
<id_product><![CDATA[109402]]></id_product>
<position><![CDATA[108965]]></position>
</category_product>
<category_product><id_category><![CDATA[2]]></id_category>
<id_product><![CDATA[109403]]></id_product>
<position><![CDATA[108966]]></position>
</category_product>
<category_product><id_category><![CDATA[2]]></id_category>
<id_product><![CDATA[109404]]></id_product>
<position><![CDATA[108967]]></position>
</category_product>
<category_product><id_category><![CDATA[2]]></id_category>
<id_product><![CDATA[109405]]></id_product>
<position><![CDATA[108968]]></position>
</category_product>
<category_product><id_category><![CDATA[2]]></id_category>
<id_product><![CDATA[109406]]></id_product>
<position><![CDATA[108969]]></position>
</category_product>
<category_product><id_category><![CDATA[2]]></id_category>
<id_product><![CDATA[109407]]></id_product>
<position><![CDATA[108970]]></position>
</category_product>
<category_product><id_category><![CDATA[2]]></id_category>
<id_product><![CDATA[109408]]></id_product>
<position><![CDATA[108971]]></position>
</category_product>
<category_product><id_category><![CDATA[2]]></id_category>
<id_product><![CDATA[109409]]></id_product>
<position><![CDATA[108972]]></position>
</category_product>
<category_product><id_category><![CDATA[2]]></id_category>
<id_product><![CDATA[109410]]></id_product>
<position><![CDATA[108973]]></position>
</category_product>
<category_product><id_category><![CDATA[2]]></id_category>
<id_product><![CDATA[109411]]></id_product>
<position><![CDATA[108974]]></position>
</category_product>
<category_product><id_category><![CDATA[2]]></id_category>
<id_product><![CDATA[109412]]></id_product>
<position><![CDATA[108975]]></position>
</category_product>
<category_product><id_category><![CDATA[2]]></id_category>
<id_product><![CDATA[109413]]></id_product>
<position><![CDATA[108976]]></position>
</category_product>
<category_product><id_category><![CDATA[2]]></id_category>
<id_product><![CDATA[109414]]></id_product>
<position><![CDATA[108977]]></position>
</category_product>
<category_product><id_category><![CDATA[2]]></id_category>
<id_product><![CDATA[109415]]></id_product>
<position><![CDATA[108978]]></position>
</category_product>
<category_product><id_category><![CDATA[2]]></id_category>
<id_product><![CDATA[109416]]></id_product>
<position><![CDATA[108979]]></position>
</category_product>
<category_product><id_category><![CDATA[2]]></id_category>
<id_product><![CDATA[109417]]></id_product>
<position><![CDATA[108980]]></position>
</category_product>
<category_product><id_category><![CDATA[2]]></id_category>
<id_product><![CDATA[109418]]></id_product>
<position><![CDATA[108981]]></position>
</category_product>
<category_product><id_category><![CDATA[2]]></id_category>
<id_product><![CDATA[109419]]></id_product>
<position><![CDATA[108982]]></position>
</category_product>
<category_product><id_category><![CDATA[2]]></id_category>
<id_product><![CDATA[109420]]></id_product>
<position><![CDATA[108983]]></position>
</category_product>
<category_product><id_category><![CDATA[2]]></id_category>
<id_product><![CDATA[109421]]></id_product>
<position><![CDATA[108984]]></position>
</category_product>
<category_product><id_category><![CDATA[2]]></id_category>
<id_product><![CDATA[109422]]></id_product>
<position><![CDATA[108985]]></position>
</category_product>
<category_product><id_category><![CDATA[2]]></id_category>
<id_product><![CDATA[109423]]></id_product>
<position><![CDATA[108986]]></position>
</category_product>
<category_product><id_category><![CDATA[2]]></id_category>
<id_product><![CDATA[109424]]></id_product>
<position><![CDATA[108987]]></position>
</category_product>
<category_product><id_category><![CDATA[2]]></id_category>
<id_product><![CDATA[109425]]></id_product>
<position><![CDATA[108988]]></position>
</category_product>
<category_product><id_category><![CDATA[2]]></id_category>
<id_product><![CDATA[109426]]></id_product>
<position><![CDATA[108989]]></position>
</category_product>
<category_product><id_category><![CDATA[2]]></id_category>
<id_product><![CDATA[109427]]></id_product>
<position><![CDATA[108990]]></position>
</category_product>
<category_product><id_category><![CDATA[2]]></id_category>
<id_product><![CDATA[109428]]></id_product>
<position><![CDATA[108991]]></position>
</category_product>
<category_product><id_category><![CDATA[2]]></id_category>
<id_product><![CDATA[109429]]></id_product>
<position><![CDATA[108992]]></position>
</category_product>
<category_product><id_category><![CDATA[2]]></id_category>
<id_product><![CDATA[109430]]></id_product>
<position><![CDATA[108993]]></position>
</category_product>
<category_product><id_category><![CDATA[2]]></id_category>
<id_product><![CDATA[109431]]></id_product>
<position><![CDATA[108994]]></position>
</category_product>
<category_product><id_category><![CDATA[2]]></id_category>
<id_product><![CDATA[109432]]></id_product>
<position><![CDATA[108995]]></position>
</category_product>
<category_product><id_category><![CDATA[2]]></id_category>
<id_product><![CDATA[109433]]></id_product>
<position><![CDATA[108996]]></position>
</category_product>
<category_product><id_category><![CDATA[2]]></id_category>
<id_product><![CDATA[109434]]></id_product>
<position><![CDATA[108997]]></position>
</category_product>
<category_product><id_category><![CDATA[2]]></id_category>
<id_product><![CDATA[109435]]></id_product>
<position><![CDATA[108998]]></position>
</category_product>
<category_product><id_category><![CDATA[2]]></id_category>
<id_product><![CDATA[109436]]></id_product>
<position><![CDATA[108999]]></position>
</category_product>
<category_product><id_category><![CDATA[2]]></id_category>
<id_product><![CDATA[109437]]></id_product>
<position><![CDATA[109000]]></position>
</category_product>
<category_product><id_category><![CDATA[2]]></id_category>
<id_product><![CDATA[109438]]></id_product>
<position><![CDATA[109001]]></position>
</category_product>
<category_product><id_category><![CDATA[2]]></id_category>
<id_product><![CDATA[109439]]></id_product>
<position><![CDATA[109002]]></position>
</category_product>
<category_product><id_category><![CDATA[2]]></id_category>
<id_product><![CDATA[109440]]></id_product>
<position><![CDATA[109003]]></position>
</category_product>
<category_product><id_category><![CDATA[2]]></id_category>
<id_product><![CDATA[109441]]></id_product>
<position><![CDATA[109004]]></position>
</category_product>
<category_product><id_category><![CDATA[2]]></id_category>
<id_product><![CDATA[109442]]></id_product>
<position><![CDATA[109005]]></position>
</category_product>
<category_product><id_category><![CDATA[2]]></id_category>
<id_product><![CDATA[109443]]></id_product>
<position><![CDATA[109006]]></position>
</category_product>
<category_product><id_category><![CDATA[2]]></id_category>
<id_product><![CDATA[109444]]></id_product>
<position><![CDATA[109007]]></position>
</category_product>
<category_product><id_category><![CDATA[2]]></id_category>
<id_product><![CDATA[109445]]></id_product>
<position><![CDATA[109008]]></position>
</category_product>
<category_product><id_category><![CDATA[2]]></id_category>
<id_product><![CDATA[109446]]></id_product>
<position><![CDATA[109009]]></position>
</category_product>
<category_product><id_category><![CDATA[2]]></id_category>
<id_product><![CDATA[109447]]></id_product>
<position><![CDATA[109010]]></position>
</category_product>
<category_product><id_category><![CDATA[2]]></id_category>
<id_product><![CDATA[109448]]></id_product>
<position><![CDATA[109011]]></position>
</category_product>
<category_product><id_category><![CDATA[2]]></id_category>
<id_product><![CDATA[109449]]></id_product>
<position><![CDATA[109012]]></position>
</category_product>
<category_product><id_category><![CDATA[2]]></id_category>
<id_product><![CDATA[109450]]></id_product>
<position><![CDATA[109013]]></position>
</category_product>
<category_product><id_category><![CDATA[2]]></id_category>
<id_product><![CDATA[109451]]></id_product>
<position><![CDATA[109014]]></position>
</category_product>
<category_product><id_category><![CDATA[2]]></id_category>
<id_product><![CDATA[109452]]></id_product>
<position><![CDATA[109015]]></position>
</category_product>
<category_product><id_category><![CDATA[2]]></id_category>
<id_product><![CDATA[109453]]></id_product>
<position><![CDATA[109016]]></position>
</category_product>
<category_product><id_category><![CDATA[2]]></id_category>
<id_product><![CDATA[109454]]></id_product>
<position><![CDATA[109017]]></position>
</category_product>
<category_product><id_category><![CDATA[2]]></id_category>
<id_product><![CDATA[109455]]></id_product>
<position><![CDATA[109018]]></position>
</category_product>
<category_product><id_category><![CDATA[2]]></id_category>
<id_product><![CDATA[109456]]></id_product>
<position><![CDATA[109019]]></position>
</category_product>
<category_product><id_category><![CDATA[2]]></id_category>
<id_product><![CDATA[109457]]></id_product>
<position><![CDATA[109020]]></position>
</category_product>
<category_product><id_category><![CDATA[2]]></id_category>
<id_product><![CDATA[109458]]></id_product>
<position><![CDATA[109021]]></position>
</category_product>
<category_product><id_category><![CDATA[2]]></id_category>
<id_product><![CDATA[109459]]></id_product>
<position><![CDATA[109022]]></position>
</category_product>
<category_product><id_category><![CDATA[2]]></id_category>
<id_product><![CDATA[109460]]></id_product>
<position><![CDATA[109023]]></position>
</category_product>
<category_product><id_category><![CDATA[2]]></id_category>
<id_product><![CDATA[109461]]></id_product>
<position><![CDATA[109024]]></position>
</category_product>
<category_product><id_category><![CDATA[2]]></id_category>
<id_product><![CDATA[109462]]></id_product>
<position><![CDATA[109025]]></position>
</category_product>
<category_product><id_category><![CDATA[2]]></id_category>
<id_product><![CDATA[109463]]></id_product>
<position><![CDATA[109026]]></position>
</category_product>
<category_product><id_category><![CDATA[2]]></id_category>
<id_product><![CDATA[109464]]></id_product>
<position><![CDATA[109027]]></position>
</category_product>
<category_product><id_category><![CDATA[2]]></id_category>
<id_product><![CDATA[109465]]></id_product>
<position><![CDATA[109028]]></position>
</category_product>
<category_product><id_category><![CDATA[2]]></id_category>
<id_product><![CDATA[109466]]></id_product>
<position><![CDATA[109029]]></position>
</category_product>
<category_product><id_category><![CDATA[2]]></id_category>
<id_product><![CDATA[109467]]></id_product>
<position><![CDATA[109030]]></position>
</category_product>
<category_product><id_category><![CDATA[2]]></id_category>
<id_product><![CDATA[109468]]></id_product>
<position><![CDATA[109031]]></position>
</category_product>
<category_product><id_category><![CDATA[2]]></id_category>
<id_product><![CDATA[109469]]></id_product>
<position><![CDATA[109032]]></position>
</category_product>
<category_product><id_category><![CDATA[2]]></id_category>
<id_product><![CDATA[109470]]></id_product>
<position><![CDATA[109033]]></position>
</category_product>
<category_product><id_category><![CDATA[2]]></id_category>
<id_product><![CDATA[109471]]></id_product>
<position><![CDATA[109034]]></position>
</category_product>
<category_product><id_category><![CDATA[2]]></id_category>
<id_product><![CDATA[109472]]></id_product>
<position><![CDATA[109035]]></position>
</category_product>
<category_product><id_category><![CDATA[2]]></id_category>
<id_product><![CDATA[109473]]></id_product>
<position><![CDATA[109036]]></position>
</category_product>
<category_product><id_category><![CDATA[2]]></id_category>
<id_product><![CDATA[109474]]></id_product>
<position><![CDATA[109037]]></position>
</category_product>
<category_product><id_category><![CDATA[2]]></id_category>
<id_product><![CDATA[109475]]></id_product>
<position><![CDATA[109038]]></position>
</category_product>
<category_product><id_category><![CDATA[2]]></id_category>
<id_product><![CDATA[109476]]></id_product>
<position><![CDATA[109039]]></position>
</category_product>
<category_product><id_category><![CDATA[2]]></id_category>
<id_product><![CDATA[109477]]></id_product>
<position><![CDATA[109040]]></position>
</category_product>
<category_product><id_category><![CDATA[2]]></id_category>
<id_product><![CDATA[109478]]></id_product>
<position><![CDATA[109041]]></position>
</category_product>
<category_product><id_category><![CDATA[2]]></id_category>
<id_product><![CDATA[109479]]></id_product>
<position><![CDATA[109042]]></position>
</category_product>
<category_product><id_category><![CDATA[2]]></id_category>
<id_product><![CDATA[109480]]></id_product>
<position><![CDATA[109043]]></position>
</category_product>
<category_product><id_category><![CDATA[2]]></id_category>
<id_product><![CDATA[109481]]></id_product>
<position><![CDATA[109044]]></position>
</category_product>
<category_product><id_category><![CDATA[2]]></id_category>
<id_product><![CDATA[109482]]></id_product>
<position><![CDATA[109045]]></position>
</category_product>
<category_product><id_category><![CDATA[2]]></id_category>
<id_product><![CDATA[109483]]></id_product>
<position><![CDATA[109046]]></position>
</category_product>
<category_product><id_category><![CDATA[2]]></id_category>
<id_product><![CDATA[109484]]></id_product>
<position><![CDATA[109047]]></position>
</category_product>
<category_product><id_category><![CDATA[2]]></id_category>
<id_product><![CDATA[109485]]></id_product>
<position><![CDATA[109048]]></position>
</category_product>
<category_product><id_category><![CDATA[2]]></id_category>
<id_product><![CDATA[109486]]></id_product>
<position><![CDATA[109049]]></position>
</category_product>
<category_product><id_category><![CDATA[2]]></id_category>
<id_product><![CDATA[109487]]></id_product>
<position><![CDATA[109050]]></position>
</category_product>
<category_product><id_category><![CDATA[2]]></id_category>
<id_product><![CDATA[109488]]></id_product>
<position><![CDATA[109051]]></position>
</category_product>
<category_product><id_category><![CDATA[2]]></id_category>
<id_product><![CDATA[109489]]></id_product>
<position><![CDATA[109052]]></position>
</category_product>
<category_product><id_category><![CDATA[2]]></id_category>
<id_product><![CDATA[109490]]></id_product>
<position><![CDATA[109053]]></position>
</category_product>
<category_product><id_category><![CDATA[2]]></id_category>
<id_product><![CDATA[109491]]></id_product>
<position><![CDATA[109054]]></position>
</category_product>
<category_product><id_category><![CDATA[2]]></id_category>
<id_product><![CDATA[109492]]></id_product>
<position><![CDATA[109055]]></position>
</category_product>
<category_product><id_category><![CDATA[2]]></id_category>
<id_product><![CDATA[109493]]></id_product>
<position><![CDATA[109056]]></position>
</category_product>
<category_product><id_category><![CDATA[2]]></id_category>
<id_product><![CDATA[109494]]></id_product>
<position><![CDATA[109057]]></position>
</category_product>
<category_product><id_category><![CDATA[2]]></id_category>
<id_product><![CDATA[109495]]></id_product>
<position><![CDATA[109058]]></position>
</category_product>
<category_product><id_category><![CDATA[2]]></id_category>
<id_product><![CDATA[109496]]></id_product>
<position><![CDATA[109059]]></position>
</category_product>
<category_product><id_category><![CDATA[2]]></id_category>
<id_product><![CDATA[109497]]></id_product>
<position><![CDATA[109060]]></position>
</category_product>
<category_product><id_category><![CDATA[2]]></id_category>
<id_product><![CDATA[109498]]></id_product>
<position><![CDATA[109061]]></position>
</category_product>
<category_product><id_category><![CDATA[2]]></id_category>
<id_product><![CDATA[109499]]></id_product>
<position><![CDATA[109062]]></position>
</category_product>
<category_product><id_category><![CDATA[2]]></id_category>
<id_product><![CDATA[109500]]></id_product>
<position><![CDATA[109063]]></position>
</category_product>
<category_product><id_category><![CDATA[2]]></id_category>
<id_product><![CDATA[109501]]></id_product>
<position><![CDATA[109064]]></position>
</category_product>
<category_product><id_category><![CDATA[2]]></id_category>
<id_product><![CDATA[109502]]></id_product>
<position><![CDATA[109065]]></position>
</category_product>
<category_product><id_category><![CDATA[2]]></id_category>
<id_product><![CDATA[109503]]></id_product>
<position><![CDATA[109066]]></position>
</category_product>
<category_product><id_category><![CDATA[2]]></id_category>
<id_product><![CDATA[109504]]></id_product>
<position><![CDATA[109067]]></position>
</category_product>
<category_product><id_category><![CDATA[2]]></id_category>
<id_product><![CDATA[109505]]></id_product>
<position><![CDATA[109068]]></position>
</category_product>
<category_product><id_category><![CDATA[2]]></id_category>
<id_product><![CDATA[109506]]></id_product>
<position><![CDATA[109069]]></position>
</category_product>
<category_product><id_category><![CDATA[2]]></id_category>
<id_product><![CDATA[109507]]></id_product>
<position><![CDATA[109070]]></position>
</category_product>
<category_product><id_category><![CDATA[2]]></id_category>
<id_product><![CDATA[109508]]></id_product>
<position><![CDATA[109071]]></position>
</category_product>
<category_product><id_category><![CDATA[2]]></id_category>
<id_product><![CDATA[109509]]></id_product>
<position><![CDATA[109072]]></position>
</category_product>
<category_product><id_category><![CDATA[2]]></id_category>
<id_product><![CDATA[109510]]></id_product>
<position><![CDATA[109073]]></position>
</category_product>
<category_product><id_category><![CDATA[2]]></id_category>
<id_product><![CDATA[109511]]></id_product>
<position><![CDATA[109074]]></position>
</category_product>
<category_product><id_category><![CDATA[2]]></id_category>
<id_product><![CDATA[109512]]></id_product>
<position><![CDATA[109075]]></position>
</category_product>
<category_product><id_category><![CDATA[2]]></id_category>
<id_product><![CDATA[109513]]></id_product>
<position><![CDATA[109076]]></position>
</category_product>
<category_product><id_category><![CDATA[2]]></id_category>
<id_product><![CDATA[109514]]></id_product>
<position><![CDATA[109077]]></position>
</category_product>
<category_product><id_category><![CDATA[2]]></id_category>
<id_product><![CDATA[109515]]></id_product>
<position><![CDATA[109078]]></position>
</category_product>
<category_product><id_category><![CDATA[2]]></id_category>
<id_product><![CDATA[109516]]></id_product>
<position><![CDATA[109079]]></position>
</category_product>
<category_product><id_category><![CDATA[2]]></id_category>
<id_product><![CDATA[109517]]></id_product>
<position><![CDATA[109080]]></position>
</category_product>
<category_product><id_category><![CDATA[2]]></id_category>
<id_product><![CDATA[109518]]></id_product>
<position><![CDATA[109081]]></position>
</category_product>
<category_product><id_category><![CDATA[2]]></id_category>
<id_product><![CDATA[109519]]></id_product>
<position><![CDATA[109082]]></position>
</category_product>
<category_product><id_category><![CDATA[2]]></id_category>
<id_product><![CDATA[109520]]></id_product>
<position><![CDATA[109083]]></position>
</category_product>
<category_product><id_category><![CDATA[2]]></id_category>
<id_product><![CDATA[109521]]></id_product>
<position><![CDATA[109084]]></position>
</category_product>
<category_product><id_category><![CDATA[2]]></id_category>
<id_product><![CDATA[109522]]></id_product>
<position><![CDATA[109085]]></position>
</category_product>
<category_product><id_category><![CDATA[2]]></id_category>
<id_product><![CDATA[109523]]></id_product>
<position><![CDATA[109086]]></position>
</category_product>
<category_product><id_category><![CDATA[2]]></id_category>
<id_product><![CDATA[109524]]></id_product>
<position><![CDATA[109087]]></position>
</category_product>
<category_product><id_category><![CDATA[2]]></id_category>
<id_product><![CDATA[109525]]></id_product>
<position><![CDATA[109088]]></position>
</category_product>
<category_product><id_category><![CDATA[2]]></id_category>
<id_product><![CDATA[109526]]></id_product>
<position><![CDATA[109089]]></position>
</category_product>
<category_product><id_category><![CDATA[2]]></id_category>
<id_product><![CDATA[109527]]></id_product>
<position><![CDATA[109090]]></position>
</category_product>
<category_product><id_category><![CDATA[2]]></id_category>
<id_product><![CDATA[109528]]></id_product>
<position><![CDATA[109091]]></position>
</category_product>
<category_product><id_category><![CDATA[2]]></id_category>
<id_product><![CDATA[109529]]></id_product>
<position><![CDATA[109092]]></position>
</category_product>
<category_product><id_category><![CDATA[2]]></id_category>
<id_product><![CDATA[109530]]></id_product>
<position><![CDATA[109093]]></position>
</category_product>
<category_product><id_category><![CDATA[2]]></id_category>
<id_product><![CDATA[109531]]></id_product>
<position><![CDATA[109094]]></position>
</category_product>
<category_product><id_category><![CDATA[2]]></id_category>
<id_product><![CDATA[109532]]></id_product>
<position><![CDATA[109094]]></position>
</category_product>
<category_product><id_category><![CDATA[2]]></id_category>
<id_product><![CDATA[109533]]></id_product>
<position><![CDATA[109095]]></position>
</category_product>
<category_product><id_category><![CDATA[2]]></id_category>
<id_product><![CDATA[109534]]></id_product>
<position><![CDATA[109096]]></position>
</category_product>
<category_product><id_category><![CDATA[2]]></id_category>
<id_product><![CDATA[109535]]></id_product>
<position><![CDATA[109097]]></position>
</category_product>
<category_product><id_category><![CDATA[2]]></id_category>
<id_product><![CDATA[109536]]></id_product>
<position><![CDATA[109098]]></position>
</category_product>
<category_product><id_category><![CDATA[2]]></id_category>
<id_product><![CDATA[109537]]></id_product>
<position><![CDATA[109099]]></position>
</category_product>
<category_product><id_category><![CDATA[2]]></id_category>
<id_product><![CDATA[109538]]></id_product>
<position><![CDATA[109100]]></position>
</category_product>
<category_product><id_category><![CDATA[2]]></id_category>
<id_product><![CDATA[109539]]></id_product>
<position><![CDATA[109101]]></position>
</category_product>
<category_product><id_category><![CDATA[2]]></id_category>
<id_product><![CDATA[109540]]></id_product>
<position><![CDATA[109102]]></position>
</category_product>
<category_product><id_category><![CDATA[2]]></id_category>
<id_product><![CDATA[109541]]></id_product>
<position><![CDATA[109103]]></position>
</category_product>
<category_product><id_category><![CDATA[2]]></id_category>
<id_product><![CDATA[109542]]></id_product>
<position><![CDATA[109104]]></position>
</category_product>
<category_product><id_category><![CDATA[2]]></id_category>
<id_product><![CDATA[109543]]></id_product>
<position><![CDATA[109105]]></position>
</category_product>
<category_product><id_category><![CDATA[2]]></id_category>
<id_product><![CDATA[109544]]></id_product>
<position><![CDATA[109106]]></position>
</category_product>
<category_product><id_category><![CDATA[2]]></id_category>
<id_product><![CDATA[109545]]></id_product>
<position><![CDATA[109107]]></position>
</category_product>
<category_product><id_category><![CDATA[2]]></id_category>
<id_product><![CDATA[109546]]></id_product>
<position><![CDATA[109108]]></position>
</category_product>
<category_product><id_category><![CDATA[2]]></id_category>
<id_product><![CDATA[109547]]></id_product>
<position><![CDATA[109109]]></position>
</category_product>
<category_product><id_category><![CDATA[2]]></id_category>
<id_product><![CDATA[109548]]></id_product>
<position><![CDATA[109110]]></position>
</category_product>
<category_product><id_category><![CDATA[2]]></id_category>
<id_product><![CDATA[109549]]></id_product>
<position><![CDATA[109111]]></position>
</category_product>
<category_product><id_category><![CDATA[2]]></id_category>
<id_product><![CDATA[109550]]></id_product>
<position><![CDATA[109112]]></position>
</category_product>
<category_product><id_category><![CDATA[2]]></id_category>
<id_product><![CDATA[109551]]></id_product>
<position><![CDATA[109113]]></position>
</category_product>
<category_product><id_category><![CDATA[2]]></id_category>
<id_product><![CDATA[109552]]></id_product>
<position><![CDATA[109114]]></position>
</category_product>
<category_product><id_category><![CDATA[2]]></id_category>
<id_product><![CDATA[109553]]></id_product>
<position><![CDATA[109115]]></position>
</category_product>
<category_product><id_category><![CDATA[2]]></id_category>
<id_product><![CDATA[109554]]></id_product>
<position><![CDATA[109116]]></position>
</category_product>
<category_product><id_category><![CDATA[2]]></id_category>
<id_product><![CDATA[109555]]></id_product>
<position><![CDATA[109117]]></position>
</category_product>
<category_product><id_category><![CDATA[2]]></id_category>
<id_product><![CDATA[109556]]></id_product>
<position><![CDATA[109118]]></position>
</category_product>
<category_product><id_category><![CDATA[2]]></id_category>
<id_product><![CDATA[109557]]></id_product>
<position><![CDATA[109119]]></position>
</category_product>
<category_product><id_category><![CDATA[2]]></id_category>
<id_product><![CDATA[109558]]></id_product>
<position><![CDATA[109120]]></position>
</category_product>
<category_product><id_category><![CDATA[2]]></id_category>
<id_product><![CDATA[109559]]></id_product>
<position><![CDATA[109121]]></position>
</category_product>
<category_product><id_category><![CDATA[2]]></id_category>
<id_product><![CDATA[109560]]></id_product>
<position><![CDATA[109122]]></position>
</category_product>
<category_product><id_category><![CDATA[2]]></id_category>
<id_product><![CDATA[109561]]></id_product>
<position><![CDATA[109123]]></position>
</category_product>
<category_product><id_category><![CDATA[2]]></id_category>
<id_product><![CDATA[109562]]></id_product>
<position><![CDATA[109124]]></position>
</category_product>
<category_product><id_category><![CDATA[2]]></id_category>
<id_product><![CDATA[109563]]></id_product>
<position><![CDATA[109125]]></position>
</category_product>
<category_product><id_category><![CDATA[2]]></id_category>
<id_product><![CDATA[109564]]></id_product>
<position><![CDATA[109126]]></position>
</category_product>
<category_product><id_category><![CDATA[2]]></id_category>
<id_product><![CDATA[109565]]></id_product>
<position><![CDATA[109127]]></position>
</category_product>
<category_product><id_category><![CDATA[2]]></id_category>
<id_product><![CDATA[109566]]></id_product>
<position><![CDATA[109128]]></position>
</category_product>
<category_product><id_category><![CDATA[2]]></id_category>
<id_product><![CDATA[109567]]></id_product>
<position><![CDATA[109129]]></position>
</category_product>
<category_product><id_category><![CDATA[2]]></id_category>
<id_product><![CDATA[109568]]></id_product>
<position><![CDATA[109130]]></position>
</category_product>
<category_product><id_category><![CDATA[2]]></id_category>
<id_product><![CDATA[109569]]></id_product>
<position><![CDATA[109131]]></position>
</category_product>
<category_product><id_category><![CDATA[2]]></id_category>
<id_product><![CDATA[109570]]></id_product>
<position><![CDATA[109132]]></position>
</category_product>
<category_product><id_category><![CDATA[2]]></id_category>
<id_product><![CDATA[109571]]></id_product>
<position><![CDATA[109133]]></position>
</category_product>
<category_product><id_category><![CDATA[2]]></id_category>
<id_product><![CDATA[109572]]></id_product>
<position><![CDATA[109134]]></position>
</category_product>
<category_product><id_category><![CDATA[2]]></id_category>
<id_product><![CDATA[109573]]></id_product>
<position><![CDATA[109135]]></position>
</category_product>
<category_product><id_category><![CDATA[2]]></id_category>
<id_product><![CDATA[109574]]></id_product>
<position><![CDATA[109136]]></position>
</category_product>
<category_product><id_category><![CDATA[2]]></id_category>
<id_product><![CDATA[109575]]></id_product>
<position><![CDATA[109137]]></position>
</category_product>
<category_product><id_category><![CDATA[2]]></id_category>
<id_product><![CDATA[109576]]></id_product>
<position><![CDATA[109138]]></position>
</category_product>
<category_product><id_category><![CDATA[2]]></id_category>
<id_product><![CDATA[109577]]></id_product>
<position><![CDATA[109139]]></position>
</category_product>
<category_product><id_category><![CDATA[2]]></id_category>
<id_product><![CDATA[109578]]></id_product>
<position><![CDATA[109140]]></position>
</category_product>
<category_product><id_category><![CDATA[2]]></id_category>
<id_product><![CDATA[109579]]></id_product>
<position><![CDATA[109141]]></position>
</category_product>
<category_product><id_category><![CDATA[2]]></id_category>
<id_product><![CDATA[109580]]></id_product>
<position><![CDATA[109142]]></position>
</category_product>
<category_product><id_category><![CDATA[2]]></id_category>
<id_product><![CDATA[109581]]></id_product>
<position><![CDATA[109143]]></position>
</category_product>
<category_product><id_category><![CDATA[2]]></id_category>
<id_product><![CDATA[109582]]></id_product>
<position><![CDATA[109144]]></position>
</category_product>
<category_product><id_category><![CDATA[2]]></id_category>
<id_product><![CDATA[109583]]></id_product>
<position><![CDATA[109145]]></position>
</category_product>
<category_product><id_category><![CDATA[2]]></id_category>
<id_product><![CDATA[109584]]></id_product>
<position><![CDATA[109146]]></position>
</category_product>
<category_product><id_category><![CDATA[2]]></id_category>
<id_product><![CDATA[109585]]></id_product>
<position><![CDATA[109147]]></position>
</category_product>
<category_product><id_category><![CDATA[2]]></id_category>
<id_product><![CDATA[109586]]></id_product>
<position><![CDATA[109148]]></position>
</category_product>
<category_product><id_category><![CDATA[2]]></id_category>
<id_product><![CDATA[109587]]></id_product>
<position><![CDATA[109149]]></position>
</category_product>
<category_product><id_category><![CDATA[2]]></id_category>
<id_product><![CDATA[109588]]></id_product>
<position><![CDATA[109150]]></position>
</category_product>
<category_product><id_category><![CDATA[2]]></id_category>
<id_product><![CDATA[109589]]></id_product>
<position><![CDATA[109151]]></position>
</category_product>
<category_product><id_category><![CDATA[2]]></id_category>
<id_product><![CDATA[109590]]></id_product>
<position><![CDATA[109152]]></position>
</category_product>
<category_product><id_category><![CDATA[2]]></id_category>
<id_product><![CDATA[109591]]></id_product>
<position><![CDATA[109153]]></position>
</category_product>
</entity_profile>
